algomancy_cli/__init__.py
algomancy_cli/cli_configuration.py
algomancy_cli/cli_launcher.py
algomancy_cli/cli_shell.py
algomancy_cli/main.py
algomancy_cli-0.3.18.dist-info/WHEEL
algomancy_cli-0.3.18.dist-info/METADATA
algomancy_cli-0.3.18.dist-info/RECORD
