Metadata-Version: 2.3
Name: algomancy-cli
Version: 0.3.18
Summary: CLI shell for Algomancy to exercise backend functionality without the GUI.
Requires-Dist: algomancy-utils
Requires-Dist: algomancy-scenario
Requires-Dist: algomancy-data
Requires-Python: >=3.14
